AUTHORS.rst
CHANGELOG.rst
LICENSE
MANIFEST.in
README.rst
setup.py
django_gizmo.egg-info/PKG-INFO
django_gizmo.egg-info/SOURCES.txt
django_gizmo.egg-info/dependency_links.txt
django_gizmo.egg-info/not-zip-safe
django_gizmo.egg-info/requires.txt
django_gizmo.egg-info/top_level.txt
gizmo/__init__.py
gizmo/models.py
gizmo/templatetags/__init__.py
gizmo/templatetags/__init__.pyc
gizmo/templatetags/gizmo_inclusion_tags.py
gizmo/templatetags/gizmo_test_tags.py
gizmo/tests/__init__.py
gizmo/tests/empty_gizmos.py
gizmo/tests/gizmos.py
gizmo/tests/urls.py