Metadata-Version: 1.0
Name: django-gizmo
Version: 0.0.4
Summary: Django app allowing for configurable targetting of template inclusion tags.
Home-page: http://github.com/praekelt/django-gizmo
Author: Praekelt Foundation
Author-email: dev@praekelt.com
License: BSD
Platform: UNKNOWN
Classifier: Programming Language :: Python
Classifier: License :: OSI Approved :: BSD License
Classifier: Development Status :: 4 - Beta
Classifier: Operating System :: OS Independent
Classifier: Framework :: Django
Classifier: Intended Audience :: Developers
Classifier: Topic :: Internet :: WWW/HTTP :: Dynamic Content
